{
    "context_service_registry": [
        {
            "key": "provinces",
            "name": "Provinces",
            "description": null,
            "url": "https://maps.kartoza.com/web/?map=/web/kartoza/kartoza.qgs",
            "query_type": "WFS",
            "result_regex": "qgs:provname",
            "time_to_live": 604800,
            "srid": 3857,
            "layer_typename": "sa_provinces",
            "service_version": "1.0.0",
            "provenance": "",
            "notes": "",
            "licensing": ""
        },
        {
            "key": "water_management_area",
            "name": "Water Management Area",
            "description": null,
            "url": "https://maps.kartoza.com/web/?map=/web/kartoza/kartoza.qgs",
            "query_type": "WFS",
            "result_regex": "qgs:name",
            "time_to_live": 604800,
            "srid": 4326,
            "layer_typename": "water_management_area",
            "service_version": "1.0.0"
        },
        {
            "key": "primary_catchment_area",
            "name": "Primary Catchment Area",
            "description": null,
            "url": "https://maps.kartoza.com/web/?map=/web/kartoza/kartoza.qgs",
            "query_type": "WFS",
            "result_regex": "qgs:name",
            "time_to_live": 604800,
            "srid": 3857,
            "layer_typename": "primary_catchment_area",
            "service_version": "1.0.0"
        },
        {
            "key": "secondary_catchment_area",
            "name": "Secondary Catchment Area",
            "description": null,
            "url": "https://maps.kartoza.com/web/?map=/web/kartoza/kartoza.qgs",
            "query_type": "WFS",
            "result_regex": "qgs:name",
            "time_to_live": 604800,
            "srid": 3857,
            "layer_typename": "secondary_catchment_area",
            "service_version": "1.0.0"
        },
        {
            "key": "tertiary_catchment_area",
            "name": "Tertiary Catchment Area",
            "description": null,
            "url": "https://maps.kartoza.com/web/?map=/web/kartoza/kartoza.qgs",
            "query_type": "WFS",
            "result_regex": "qgs:name",
            "time_to_live": 604800,
            "srid": 3857,
            "layer_typename": "tertiary_catchment_area",
            "service_version": "1.0.0"
        },
        {
            "key": "quaternary_catchment_area",
            "name": "Quaternary Catchment Area",
            "description": null,
            "url": "https://maps.kartoza.com/web/?map=/web/kartoza/kartoza.qgs",
            "query_type": "WFS",
            "result_regex": "qgs:name",
            "time_to_live": 604800,
            "srid": 3857,
            "layer_typename": "quaternary_catchment_area",
            "service_version": "1.0.0"
        },
        {
            "key": "provinces_geoserver",
             "name": "Province GeoServer",
             "description": null,
             "url": "https://maps.kartoza.com/geoserver/wfs",
             "query_type": "WFS",
             "result_regex": "qgs:id",
             "time_to_live": 604800,
             "srid": 3857,
             "layer_typename": "kartoza:sa_provinces",
             "service_version": "1.0.0"
        },
        {
            "key": "farm_portion",
            "name": "Farm Portion",
            "description": null,
            "url": "https://maps.kartoza.com/geoserver/wfs",
            "query_type": "WFS",
            "result_regex": "qgs:id",
            "time_to_live": 604800,
            "srid": 3857,
            "layer_typename": "kartoza:farm_portion",
            "service_version": "1.0.0"
        },
        {
            "key": "erf",
            "name": "Erven Boundaries",
            "description": null,
            "url": "https://maps.kartoza.com/geoserver/wfs",
            "query_type": "WFS",
            "result_regex": "qgs:id",
            "time_to_live": 604800,
            "srid": 4326,
            "layer_typename": "kartoza:erf",
            "service_version": "1.0.0"
        },
        {
            "key": "district_municipalities",
            "name": "District Municipalities",
            "description": null,
            "url": "https://maps.kartoza.com/geoserver/wfs",
            "query_type": "WFS",
            "result_regex": "qgs:district",
            "time_to_live": 604800,
            "srid": 3857,
            "layer_typename": "kartoza:district_municipalities",
            "service_version": "1.0.0"
        },
        {
            "key": "municipal_ward_boundaries",
            "name": "Municipal Ward Boundaries",
            "description": null,
            "url": "https://maps.kartoza.com/geoserver/wfs",
            "query_type": "WFS",
            "result_regex": "qgs:mn_name",
            "time_to_live": 604800,
            "srid": 3857,
            "layer_typename": "kartoza:municipal_ward_boundaries",
            "service_version": "1.0.0"
        },
        {
            "key": "sub_places",
            "name": "Sub Places",
            "description": null,
            "url": "https://maps.kartoza.com/geoserver/wfs",
            "query_type": "WFS",
            "result_regex": "qgs:sp_name",
            "time_to_live": 604800,
            "srid": 4326,
            "layer_typename": "kartoza:sub_places",
            "service_version": "1.0.0"
        },
        {
            "key": "vegetation_2012",
            "name": "2012 Vegetation Map of South Africa, Lesotho and Swaziland",
            "description": null,
            "url": "http://lbimsgis.kartoza.com/geoserver/wfs",
            "query_type": "WFS",
            "result_regex": "qgs:bioregion",
            "time_to_live": 604800,
            "srid": 4326,
            "layer_typename": "geonode:vegetation_map_2012",
            "service_version": "1.0.0"
        },
        {
            "key": "sa_biomes",
            "name": "2012 Biome Map of South Africa, Lesotho and Swaziland",
            "description": null,
            "url": "http://lbimsgis.kartoza.com/geoserver/wfs",
            "query_type": "WFS",
            "result_regex": "qgs:biome",
            "time_to_live": 604800,
            "srid": 4326,
            "layer_typename": "geonode:vegetation_map_2012",
            "service_version": "1.0.0"
        },
        {
            "key": "nfepa_wetlands",
            "name": "NFEPA Wetlands 2011",
            "description": null,
            "url": "http://lbimsgis.kartoza.com/geoserver/wfs",
            "query_type": "WFS",
            "result_regex": "qgs:nwcs_l4",
            "time_to_live": 604800,
            "srid": 4326,
            "layer_typename": "geonode:nfepa_wetlands",
            "service_version": "1.0.0"
        },
        {
            "key": "rehabilitated_wetlands",
            "name": "Rehabilitated Wetlands",
            "description": null,
            "url": "http://lbimsgis.kartoza.com/geoserver/wfs",
            "query_type": "WFS",
            "result_regex": "qgs:type",
            "time_to_live": 604800,
            "srid": 4326,
            "layer_typename": "geonode:rehabilitated_wetlands",
            "service_version": "1.0.0"
        },
        {
            "key": "wetlandcluster",
            "name": "NFEPA wetland clusters 2011",
            "description": null,
            "url": "http://lbimsgis.kartoza.com/geoserver/wfs",
            "query_type": "WFS",
            "result_regex": "qgs:majwetveg",
            "time_to_live": 604800,
            "srid": 4326,
            "layer_typename": "geonode:wetlandcluster",
            "service_version": "1.0.0"
        },
        {
            "key": "dams500g",
            "name": "South Africa Dams Polygon",
            "description": null,
            "url": "http://lbimsgis.kartoza.com/geoserver/wfs",
            "query_type": "WFS",
            "result_regex": "qgs:label",
            "time_to_live": 604800,
            "srid": 4326,
            "layer_typename": "geonode:dams500g",
            "service_version": "1.0.0"
        },
        {
            "key": "rivers500k",
            "name": "Rivers of south africa",
            "description": null,
            "url": "http://lbimsgis.kartoza.com/geoserver/wfs",
            "query_type": "WFS",
            "result_regex": "qgs:reachcode",
            "time_to_live": 604800,
            "srid": 4222,
            "layer_typename": "geonode:wriall500",
            "service_version": "1.0.0"
        },
        {
            "key": "nfepa_rivers",
            "name": "NFEPA Rivers 2011",
            "description": null,
            "url": "http://lbimsgis.kartoza.com/geoserver/wfs",
            "query_type": "WFS",
            "result_regex": "qgs:fepacode",
            "time_to_live": 604800,
            "srid": 4326,
            "layer_typename": "geonode:nfepa_rivers",
            "service_version": "1.0.0"
        },


        {
            "key": "mean_annual_temperature",
            "name": "Mean Annual Temperature (C)",
            "description": null,
            "url": "https://maps.kartoza.com/geoserver/wms",
            "query_type": "WMS",
            "result_regex": "qgs:name",
            "time_to_live": 604800,
            "srid": 4326,
            "layer_typename": "kartoza:mean_annual temperature",
            "service_version": "1.3.0"
        },
        {
            "key": "monthly_rainfall_march",
            "name": "Monthly Rainfall and its Inter-Annual Variability (March)",
            "description": null,
            "url": "https://maps.kartoza.com/geoserver/wms",
            "query_type": "WMS",
            "result_regex": "kartoza:GRAY_INDEX",
            "time_to_live": 604800,
            "srid": 4326,
            "layer_typename": "kartoza:gmednrfl3",
            "service_version": "1.3.0"
        },
        {
            "key": "monthly_rainfall_april",
            "name": "Monthly Rainfall and its Inter-Annual Variability (April)",
            "description": null,
            "url": "https://maps.kartoza.com/geoserver/wms",
            "query_type": "WMS",
            "result_regex": "kartoza:GRAY_INDEX",
            "time_to_live": 604800,
            "srid": 3857,
            "layer_typename": "kartoza:gmednrfl4",
            "service_version": "1.3.0"
        },
        {
            "key": "monthly_rainfall_may",
            "name": "Monthly Rainfall and its Inter-Annual Variability (May)",
            "description": null,
            "url": "https://maps.kartoza.com/geoserver/wms",
            "query_type": "WMS",
            "result_regex": "kartoza:GRAY_INDEX",
            "time_to_live": 604800,
            "srid": 3857,
            "layer_typename": "kartoza:gmednrfl5",
            "service_version": "1.3.0"
        },
        {
            "key": "monthly_rainfall_june",
            "name": "Monthly Rainfall and its Inter-Annual Variability (June)",
            "description": null,
            "url": "https://maps.kartoza.com/geoserver/wms",
            "query_type": "WMS",
            "result_regex": "kartoza:GRAY_INDEX",
            "time_to_live": 604800,
            "srid": 3857,
            "layer_typename": "kartoza:gmednrfl6",
            "service_version": "1.3.0"
        },
        {
            "key": "monthly_rainfall_july",
             "name": "Monthly Rainfall and its Inter-Annual Variability (July)",
             "description": null,
             "url": "https://maps.kartoza.com/geoserver/wms",
             "query_type": "WMS",
             "result_regex": "kartoza:GRAY_INDEX",
             "time_to_live": 604800,
             "srid": 3857,
             "layer_typename": "kartoza:gmednrfl7",
             "service_version": "1.3.0"
        },
        {
            "key": "monthly_rainfall_august",
            "name": "Monthly Rainfall and its Inter-Annual Variability (August)",
            "description": null,
            "url": "https://maps.kartoza.com/geoserver/wms",
            "query_type": "WMS",
            "result_regex": "kartoza:GRAY_INDEX",
            "time_to_live": 604800,
            "srid": 3857,
            "layer_typename": "kartoza:gmednrfl8",
            "service_version": "1.3.0"
        },
        {
            "key": "monthly_rainfall_september",
            "name": "Monthly Rainfall and its Inter-Annual Variability (September)",
            "description": null,
            "url": "https://maps.kartoza.com/geoserver/wms",
            "query_type": "WMS",
            "result_regex": "kartoza:GRAY_INDEX",
            "time_to_live": 604800,
            "srid": 4326,
            "layer_typename": "kartoza:gmednrfl9",
            "service_version": "1.3.0"
        },
        {
            "key": "monthly_rainfall_october",
            "name": "Monthly Rainfall and its Inter-Annual Variability (October)",
            "description": null,
            "url": "https://maps.kartoza.com/geoserver/wms",
            "query_type": "WMS",
            "result_regex": "kartoza:GRAY_INDEX",
            "time_to_live": 604800,
            "srid": 3857,
            "layer_typename": "kartoza:gmednrfl10",
            "service_version": "1.3.0"
        },
        {
            "key": "monthly_rainfall_november",
            "name": "Monthly Rainfall and its Inter-Annual Variability (November)",
            "description": null,
            "url": "https://maps.kartoza.com/geoserver/wms",
            "query_type": "WMS",
            "result_regex": "kartoza:GRAY_INDEX",
            "time_to_live": 604800,
            "srid": 3857,
            "layer_typename": "kartoza:gmednrfl11",
            "service_version": "1.3.0"
        },
        {
            "key": "monthly_rainfall_december",
            "name": "Monthly Rainfall and its Inter-Annual Variability (December)",
            "description": null,
            "url": "https://maps.kartoza.com/geoserver/wms",
            "query_type": "WMS",
            "result_regex": "kartoza:GRAY_INDEX",
            "time_to_live": 604800,
            "srid": 4326,
            "layer_typename": "kartoza:gmednrfl12",
            "service_version": "1.3.0"
        },




        {
            "key": "mean_maximum_temperature_january",
            "name": "Monthly Means Of Daily Maximum Temperature (C) January",
            "description": null,
            "url": "https://maps.kartoza.com/geoserver/wms",
            "query_type": "WMS",
            "result_regex": "kartoza:GRAY_INDEX",
            "time_to_live": 604800,
            "srid": 4326,
            "layer_typename": "kartoza:tmaxave01c",
            "service_version": "1.3.0"
        },
        {
            "key": "mean_maximum_temperature_february",
            "name": "Monthly Means Of Daily Maximum Temperature (C) February",
            "description": null,
            "url": "https://maps.kartoza.com/geoserver/wms",
            "query_type": "WMS",
            "result_regex": "kartoza:GRAY_INDEX",
            "time_to_live": 604800,
            "srid": 4326,
            "layer_typename": "kartoza:tmaxave02c",
            "service_version": "1.3.0"
        },
        {
            "key": "mean_maximum_temperature_march",
            "name": "Monthly Means Of Daily Maximum Temperature (C) March",
            "description": null,
            "url": "https://maps.kartoza.com/geoserver/wms",
            "query_type": "WMS",
            "result_regex": "kartoza:GRAY_INDEX",
            "time_to_live": 604800,
            "srid": 3857,
            "layer_typename": "kartoza:tmaxave03c",
            "service_version": "1.3.0"
        },
        {
            "key": "mean_maximum_temperature_april",
            "name": "Monthly Means Of Daily Maximum Temperature (C) April",
            "description": null,
            "url": "https://maps.kartoza.com/geoserver/wms",
            "query_type": "WMS",
            "result_regex": "kartoza:GRAY_INDEX",
            "time_to_live": 604800,
            "srid": 3857,
            "layer_typename": "kartoza:tmaxave04c",
            "service_version": "1.3.0"
        },
        {
            "key": "mean_maximum_temperature_may",
            "name": "Monthly Means Of Daily Maximum Temperature (C) May",
            "description": null,
            "url": "https://maps.kartoza.com/geoserver/wms",
            "query_type": "WMS",
            "result_regex": "kartoza:GRAY_INDEX",
            "time_to_live": 604800,
            "srid": 3857,
            "layer_typename": "kartoza:tmaxave05c",
            "service_version": "1.3.0"
        },
        {
            "key": "mean_maximum_temperature_june",
             "name": "Monthly Means Of Daily Maximum Temperature (C) June",
             "description": null,
             "url": "https://maps.kartoza.com/geoserver/wms",
             "query_type": "WMS",
             "result_regex": "kartoza:GRAY_INDEX",
             "time_to_live": 604800,
             "srid": 3857,
             "layer_typename": "kartoza:tmaxave06c",
             "service_version": "1.3.0"
        },
        {
            "key": "mean_maximum_temperature_july",
            "name": "Monthly Means Of Daily Maximum Temperature (C) July",
            "description": null,
            "url": "https://maps.kartoza.com/geoserver/wms",
            "query_type": "WMS",
            "result_regex": "kartoza:GRAY_INDEX",
            "time_to_live": 604800,
            "srid": 3857,
            "layer_typename": "kartoza:tmaxave07c",
            "service_version": "1.3.0"
        },
        {
            "key": "mean_maximum_temperature_august",
            "name": "Monthly Means Of Daily Maximum Temperature (C) August",
            "description": null,
            "url": "https://maps.kartoza.com/geoserver/wms",
            "query_type": "WMS",
            "result_regex": "kartoza:GRAY_INDEX",
            "time_to_live": 604800,
            "srid": 4326,
            "layer_typename": "kartoza:tmaxave08c",
            "service_version": "1.3.0"
        },
        {
            "key": "mean_maximum_temperature_september",
            "name": "Monthly Means Of Daily Maximum Temperature (C) September",
            "description": null,
            "url": "https://maps.kartoza.com/geoserver/wms",
            "query_type": "WMS",
            "result_regex": "kartoza:GRAY_INDEX",
            "time_to_live": 604800,
            "srid": 3857,
            "layer_typename": "kartoza:tmaxave09c",
            "service_version": "1.3.0"
        },
        {
            "key": "mean_maximum_temperature_october",
            "name": "Monthly Means Of Daily Maximum Temperature (C) October",
            "description": null,
            "url": "https://maps.kartoza.com/geoserver/wms",
            "query_type": "WMS",
            "result_regex": "kartoza:GRAY_INDEX",
            "time_to_live": 604800,
            "srid": 3857,
            "layer_typename": "kartoza:tmaxave10c",
            "service_version": "1.3.0"
        },
        {
            "key": "mean_maximum_temperature_november",
            "name": "Monthly Means Of Daily Maximum Temperature (C) November",
            "description": null,
            "url": "https://maps.kartoza.com/geoserver/wms",
            "query_type": "WMS",
            "result_regex": "kartoza:GRAY_INDEX",
            "time_to_live": 604800,
            "srid": 4326,
            "layer_typename": "kartoza:tmaxave11c",
            "service_version": "1.3.0"
        },
        {
            "key": "mean_maximum_temperature_december",
            "name": "Monthly Means Of Daily Maximum Temperature (C) December",
            "description": null,
            "url": "https://maps.kartoza.com/geoserver/wms",
            "query_type": "WMS",
            "result_regex": "kartoza:GRAY_INDEX",
            "time_to_live": 604800,
            "srid": 4326,
            "layer_typename": "kartoza:tmaxave12c",
            "service_version": "1.3.0"
        },

        {
            "key": "mean_average_temperature_january",
            "name": "Monthly Means Of Daily Average Temperature (C) January",
            "description": null,
            "url": "https://maps.kartoza.com/geoserver/wms",
            "query_type": "WMS",
            "result_regex": "kartoza:GRAY_INDEX",
            "time_to_live": 604800,
            "srid": 4326,
            "layer_typename": "kartoza:tmean01c",
            "service_version": "1.3.0"
        },
        {
            "key": "mean_average_temperature_february",
            "name": "Monthly Means Of Daily Average Temperature (C) February",
            "description": null,
            "url": "https://maps.kartoza.com/geoserver/wms",
            "query_type": "WMS",
            "result_regex": "kartoza:GRAY_INDEX",
            "time_to_live": 604800,
            "srid": 4326,
            "layer_typename": "kartoza:tmean02c",
            "service_version": "1.3.0"
        },
        {
            "key": "mean_average_temperature_march",
            "name": "Monthly Means Of Daily Average Temperature (C) March",
            "description": null,
            "url": "https://maps.kartoza.com/geoserver/wms",
            "query_type": "WMS",
            "result_regex": "kartoza:GRAY_INDEX",
            "time_to_live": 604800,
            "srid": 3857,
            "layer_typename": "kartoza:tmean03c",
            "service_version": "1.3.0"
        },
        {
            "key": "mean_average_temperature_april",
            "name": "Monthly Means Of Daily Average Temperature (C) April",
            "description": null,
            "url": "https://maps.kartoza.com/geoserver/wms",
            "query_type": "WMS",
            "result_regex": "kartoza:GRAY_INDEX",
            "time_to_live": 604800,
            "srid": 3857,
            "layer_typename": "kartoza:tmean04c",
            "service_version": "1.3.0"
        },
        {
            "key": "mean_average_temperature_may",
            "name": "Monthly Means Of Daily Average Temperature (C) May",
            "description": null,
            "url": "https://maps.kartoza.com/geoserver/wms",
            "query_type": "WMS",
            "result_regex": "kartoza:GRAY_INDEX",
            "time_to_live": 604800,
            "srid": 3857,
            "layer_typename": "kartoza:tmean05c",
            "service_version": "1.3.0"
        },
        {
            "key": "mean_average_temperature_june",
             "name": "Monthly Means Of Daily Average Temperature (C) June",
             "description": null,
             "url": "https://maps.kartoza.com/geoserver/wms",
             "query_type": "WMS",
             "result_regex": "kartoza:GRAY_INDEX",
             "time_to_live": 604800,
             "srid": 3857,
             "layer_typename": "kartoza:tmean06c",
             "service_version": "1.3.0"
        },
        {
            "key": "mean_average_temperature_july",
            "name": "Monthly Means Of Daily Average Temperature (C) July",
            "description": null,
            "url": "https://maps.kartoza.com/geoserver/wms",
            "query_type": "WMS",
            "result_regex": "kartoza:GRAY_INDEX",
            "time_to_live": 604800,
            "srid": 3857,
            "layer_typename": "kartoza:tmean07c",
            "service_version": "1.3.0"
        },
        {
            "key": "mean_average_temperature_august",
            "name": "Monthly Means Of Daily Average Temperature (C) August",
            "description": null,
            "url": "https://maps.kartoza.com/geoserver/wms",
            "query_type": "WMS",
            "result_regex": "kartoza:GRAY_INDEX",
            "time_to_live": 604800,
            "srid": 4326,
            "layer_typename": "kartoza:tmean08c",
            "service_version": "1.3.0"
        },
        {
            "key": "mean_average_temperature_september",
            "name": "Monthly Means Of Daily Average Temperature (C) September",
            "description": null,
            "url": "https://maps.kartoza.com/geoserver/wms",
            "query_type": "WMS",
            "result_regex": "kartoza:GRAY_INDEX",
            "time_to_live": 604800,
            "srid": 3857,
            "layer_typename": "kartoza:tmean09c",
            "service_version": "1.3.0"
        },
        {
            "key": "mean_average_temperature_october",
            "name": "Monthly Means Of Daily Average Temperature (C) October",
            "description": null,
            "url": "https://maps.kartoza.com/geoserver/wms",
            "query_type": "WMS",
            "result_regex": "kartoza:GRAY_INDEX",
            "time_to_live": 604800,
            "srid": 3857,
            "layer_typename": "kartoza:tmean10c",
            "service_version": "1.3.0"
        },
        {
            "key": "mean_average_temperature_november",
            "name": "Monthly Means Of Daily Average Temperature (C) November",
            "description": null,
            "url": "https://maps.kartoza.com/geoserver/wms",
            "query_type": "WMS",
            "result_regex": "kartoza:GRAY_INDEX",
            "time_to_live": 604800,
            "srid": 4326,
            "layer_typename": "kartoza:tmean11c",
            "service_version": "1.3.0"
        },
        {
            "key": "mean_average_temperature_december",
            "name": "Monthly Means Of Daily Average Temperature (C) December",
            "description": null,
            "url": "https://maps.kartoza.com/geoserver/wms",
            "query_type": "WMS",
            "result_regex": "kartoza:GRAY_INDEX",
            "time_to_live": 604800,
            "srid": 4326,
            "layer_typename": "kartoza:tmean12c",
            "service_version": "1.3.0"
        },

        {
            "key": "mean_standard_deviation_temperature_january",
            "name": "Standard Deviation (C) Of Daily Maximum Temperature January",
            "description": null,
            "url": "https://maps.kartoza.com/geoserver/wms",
            "query_type": "WMS",
            "result_regex": "kartoza:GRAY_INDEX",
            "time_to_live": 604800,
            "srid": 4326,
            "layer_typename": "kartoza:tmaxsdev01c",
            "service_version": "1.3.0"
        },
        {
            "key": "mean_standard_deviation_temperature_february",
            "name": "Standard Deviation (C) Of Daily Maximum Temperature February",
            "description": null,
            "url": "https://maps.kartoza.com/geoserver/wms",
            "query_type": "WMS",
            "result_regex": "kartoza:GRAY_INDEX",
            "time_to_live": 604800,
            "srid": 4326,
            "layer_typename": "kartoza:tmaxsdev02c",
            "service_version": "1.3.0"
        },
        {
            "key": "mean_standard_deviation_temperature_march",
            "name": "Standard Deviation (C) Of Daily Maximum Temperature March",
            "description": null,
            "url": "https://maps.kartoza.com/geoserver/wms",
            "query_type": "WMS",
            "result_regex": "kartoza:GRAY_INDEX",
            "time_to_live": 604800,
            "srid": 3857,
            "layer_typename": "kartoza:tmaxsdev03c",
            "service_version": "1.3.0"
        },
        {
            "key": "mean_standard_deviation_temperature_april",
            "name": "Standard Deviation (C) Of Daily Maximum Temperature April",
            "description": null,
            "url": "https://maps.kartoza.com/geoserver/wms",
            "query_type": "WMS",
            "result_regex": "kartoza:GRAY_INDEX",
            "time_to_live": 604800,
            "srid": 3857,
            "layer_typename": "kartoza:tmaxsdev04c",
            "service_version": "1.3.0"
        },
        {
            "key": "mean_standard_deviation_temperature_may",
            "name": "Standard Deviation (C) Of Daily Maximum Temperature May",
            "description": null,
            "url": "https://maps.kartoza.com/geoserver/wms",
            "query_type": "WMS",
            "result_regex": "kartoza:GRAY_INDEX",
            "time_to_live": 604800,
            "srid": 3857,
            "layer_typename": "kartoza:tmaxsdev05c",
            "service_version": "1.3.0"
        },
        {
            "key": "mean_standard_deviation_temperature_june",
             "name": "Standard Deviation (C) Of Daily Maximum Temperature June",
             "description": null,
             "url": "https://maps.kartoza.com/geoserver/wms",
             "query_type": "WMS",
             "result_regex": "kartoza:GRAY_INDEX",
             "time_to_live": 604800,
             "srid": 3857,
             "layer_typename": "kartoza:tmaxsdev06c",
             "service_version": "1.3.0"
        },
        {
            "key": "mean_standard_deviation_temperature_july",
            "name": "Standard Deviation (C) Of Daily Maximum Temperature July",
            "description": null,
            "url": "https://maps.kartoza.com/geoserver/wms",
            "query_type": "WMS",
            "result_regex": "kartoza:GRAY_INDEX",
            "time_to_live": 604800,
            "srid": 3857,
            "layer_typename": "kartoza:tmaxsdev07c",
            "service_version": "1.3.0"
        },
        {
            "key": "mean_standard_deviation_temperature_august",
            "name": "Standard Deviation (C) Of Daily Maximum Temperature August",
            "description": null,
            "url": "https://maps.kartoza.com/geoserver/wms",
            "query_type": "WMS",
            "result_regex": "kartoza:GRAY_INDEX",
            "time_to_live": 604800,
            "srid": 4326,
            "layer_typename": "kartoza:tmaxsdev08c",
            "service_version": "1.3.0"
        },
        {
            "key": "mean_standard_deviation_temperature_september",
            "name": "Standard Deviation (C) Of Daily Maximum Temperature September",
            "description": null,
            "url": "https://maps.kartoza.com/geoserver/wms",
            "query_type": "WMS",
            "result_regex": "kartoza:GRAY_INDEX",
            "time_to_live": 604800,
            "srid": 3857,
            "layer_typename": "kartoza:tmaxsdev09c",
            "service_version": "1.3.0"
        },
        {
            "key": "mean_standard_deviation_temperature_october",
            "name": "Standard Deviation (C) Of Daily Maximum Temperature October",
            "description": null,
            "url": "https://maps.kartoza.com/geoserver/wms",
            "query_type": "WMS",
            "result_regex": "kartoza:GRAY_INDEX",
            "time_to_live": 604800,
            "srid": 3857,
            "layer_typename": "kartoza:tmaxsdev10c",
            "service_version": "1.3.0"
        },
        {
            "key": "mean_standard_deviation_temperature_november",
            "name": "Standard Deviation (C) Of Daily Maximum Temperature November",
            "description": null,
            "url": "https://maps.kartoza.com/geoserver/wms",
            "query_type": "WMS",
            "result_regex": "kartoza:GRAY_INDEX",
            "time_to_live": 604800,
            "srid": 4326,
            "layer_typename": "kartoza:tmaxsdev11c",
            "service_version": "1.3.0"
        },
        {
            "key": "mean_standard_deviation_temperature_december",
            "name": "Standard Deviation (C) Of Daily Maximum Temperature December",
            "description": null,
            "url": "https://maps.kartoza.com/geoserver/wms",
            "query_type": "WMS",
            "result_regex": "kartoza:GRAY_INDEX",
            "time_to_live": 604800,
            "srid": 4326,
            "layer_typename": "kartoza:tmaxsdev12c",
            "service_version": "1.3.0"
        }

        ,
        {
            "key": "actual_vapour_pressure_january",
            "name": "Actual vapour Pressure January",
            "description": null,
            "url": "https://maps.kartoza.com/geoserver/wms",
            "query_type": "WMS",
            "result_regex": "qgs:name",
            "time_to_live": 604800,
            "srid": 4326,
            "layer_typename": "kartoza:avp01c",
            "service_version": "1.3.0"
        },
        {
            "key": "actual_vapour_pressure_february",
            "name": "Actual vapour Pressure February",
            "description": null,
            "url": "https://maps.kartoza.com/geoserver/wms",
            "query_type": "WMS",
            "result_regex": "qgs:name",
            "time_to_live": 604800,
            "srid": 4326,
            "layer_typename": "kartoza:avp02c",
            "service_version": "1.3.0"
        },
        {
            "key": "actual_vapour_pressure_march",
            "name": "Actual vapour Pressure March",
            "description": null,
            "url": "https://maps.kartoza.com/geoserver/wms",
            "query_type": "WMS",
            "result_regex": "qgs:name",
            "time_to_live": 604800,
            "srid": 4326,
            "layer_typename": "kartoza:avp03c",
            "service_version": "1.3.0"
        },
        {
            "key": "actual_vapour_pressure_april",
            "name": "Actual vapour Pressure April",
            "description": null,
            "url": "https://maps.kartoza.com/geoserver/wms",
            "query_type": "WMS",
            "result_regex": "qgs:name",
            "time_to_live": 604800,
            "srid": 4326,
            "layer_typename": "kartoza:avp04c",
            "service_version": "1.3.0"
        },
        {
            "key": "actual_vapour_pressure_may",
            "name": "Actual vapour Pressure May",
            "description": null,
            "url": "https://maps.kartoza.com/geoserver/wms",
            "query_type": "WMS",
            "result_regex": "qgs:name",
            "time_to_live": 604800,
            "srid": 4326,
            "layer_typename": "kartoza:avp05c",
            "service_version": "1.3.0"
        },
        {
            "key": "actual_vapour_pressure_july",
            "name": "Actual vapour Pressure July",
            "description": null,
            "url": "https://maps.kartoza.com/geoserver/wms",
            "query_type": "WMS",
            "result_regex": "qgs:name",
            "time_to_live": 604800,
            "srid": 4326,
            "layer_typename": "kartoza:avp07c",
            "service_version": "1.3.0"
        },
        {
            "key": "actual_vapour_pressure_august",
            "name": "Actual vapour Pressure August",
            "description": null,
            "url": "https://maps.kartoza.com/geoserver/wms",
            "query_type": "WMS",
            "result_regex": "qgs:name",
            "time_to_live": 604800,
            "srid": 4326,
            "layer_typename": "kartoza:avp08c",
            "service_version": "1.3.0"
        },
        {
            "key": "actual_vapour_pressure_october",
            "name": "Actual vapour Pressure October",
            "description": null,
            "url": "https://maps.kartoza.com/geoserver/wms",
            "query_type": "WMS",
            "result_regex": "qgs:name",
            "time_to_live": 604800,
            "srid": 4326,
            "layer_typename": "kartoza:avp010c",
            "service_version": "1.3.0"
        },
        {
            "key": "actual_vapour_pressure_november",
            "name": "Actual vapour Pressure November",
            "description": null,
            "url": "https://maps.kartoza.com/geoserver/wms",
            "query_type": "WMS",
            "result_regex": "qgs:name",
            "time_to_live": 604800,
            "srid": 4326,
            "layer_typename": "kartoza:avp011c",
            "service_version": "1.3.0"
        }





    ],
    "context_group": [
        {
            "key": "water_group",
            "name": "River Catchments",
            "description": "Layers that relate to freshwater,estuarine and maritime ecosystems",
            "context_service_registry_keys": [
                "water_management_area",
                "primary_catchment_area",
                "secondary_catchment_area",
                "tertiary_catchment_area",
                "quaternary_catchment_area",
                "nfepa_wetlands",
                "rehabilitated_wetlands",
                "dams500g",
                "rivers500k",
                "nfepa_rivers"
            ]
        },
        {
            "key": "political_boundary_group",
            "name": "Administrative Boundary",
            "description": "A collection of administrative and cadastral boundaries within South Africa",
            "context_service_registry_keys": [
                "provinces",
                "provinces_geoserver",
                "district_municipalities",
                "municipal_ward_boundaries",
                "sub_places"
            ]
        },
        {
            "key": "rainfall_group",
            "name": "Rainfall Rasters",
            "description": "A collection of rasters depicting monthly rainfall in South Africa",
            "context_service_registry_keys": [
                "monthly_rainfall_march",
                "monthly_rainfall_april",
                "monthly_rainfall_may",
                "monthly_rainfall_june",
                "monthly_rainfall_july",
                "monthly_rainfall_august",
                "monthly_rainfall_september",
                "monthly_rainfall_october",
                "monthly_rainfall_november",
                "monthly_rainfall_december"
            ]
        },

        {
            "key": "actual_vapour_group",
            "name": "Actual vapour  Rasters",
            "description": "A collection of rasters depicting vapour  in South Africa",
            "context_service_registry_keys": [
                "actual_vapour_pressure_january",
                "actual_vapour_pressure_february",
                "actual_vapour_pressure_march",
                "actual_vapour_pressure_april",
                "actual_vapour_pressure_may",
                "actual_vapour_pressure_july",
                "actual_vapour_pressure_august",
                "actual_vapour_pressure_october",
                "actual_vapour_pressure_november"

            ]
        },
        {
            "key": "mean_maximum_temperature_group",
            "name": "Monthly",
            "description": "Monthly Means Of Daily Maximum Temperature (C) January - December",
            "context_service_registry_keys": [
                "mean_maximum_temperature_january",
                "mean_maximum_temperature_february",
                "mean_maximum_temperature_march",
                "mean_maximum_temperature_april",
                "mean_maximum_temperature_may",
                "mean_maximum_temperature_june",
                "mean_maximum_temperature_july",
                "mean_maximum_temperature_august",
                "mean_maximum_temperature_september",
                "mean_maximum_temperature_october",
                "mean_maximum_temperature_november",
                "mean_maximum_temperature_december"
            ]
        },

        {
            "key": "mean_average_temperature_group",
            "name": "Monthly mean,maximum and standard deviation Rasters",
            "description": "A collection of rasters depicting monthly rainfall in South Africa",
            "context_service_registry_keys": [
                "mean_average_temperature_january",
                "mean_average_temperature_february",
                "mean_average_temperature_march",
                "mean_average_temperature_april",
                "mean_average_temperature_may",
                "mean_average_temperature_june",
                "mean_average_temperature_july",
                "mean_average_temperature_august",
                "mean_average_temperature_september",
                "mean_average_temperature_october",
                "mean_average_temperature_november",
                "mean_average_temperature_december"
            ]
        },


        {
            "key": "mean_standard_deviation_temperature_group",
            "name": "Monthly mean,maximum and standard deviation Rasters",
            "description": "A collection of rasters depicting monthly rainfall in South Africa",
            "context_service_registry_keys": [
                "mean_standard_deviation_temperature_january",
                "mean_standard_deviation_temperature_february",
                "mean_standard_deviation_temperature_march",
                "mean_standard_deviation_temperature_april",
                "mean_standard_deviation_temperature_may",
                "mean_standard_deviation_temperature_june",
                "mean_standard_deviation_temperature_july",
                "mean_standard_deviation_temperature_august",
                "mean_standard_deviation_temperature_september",
                "mean_standard_deviation_temperature_october",
                "mean_standard_deviation_temperature_november",
                "mean_standard_deviation_temperature_december"
            ]
        },
        {
            "key": "cadastre_group",
            "name": "Cadastre",
            "description": "Land demarcations from Surveyor General",
            "context_service_registry_keys": [
                "farm_portion",
                "erf"
            ]
        },
        {
            "key": "vegetation_group",
            "name": "Land Cover and Land Use",
            "description": "Layers that depict natural/artificial vegetation and also monitors land-use changes",
            "context_service_registry_keys": [
                "vegetation_2012",
                "sa_biomes"

            ]
        }
    ],
    "context_collection": [
        {
            "key": "boundary",
            "name": "Boundary Collection",
            "description": "Collection of administrative and Cadastre boundaries",
            "context_group_keys": [
                "political_boundary_group",
                "cadastre_group"
            ]
        },
        {
            "key": "river_ecosystem",
            "name": "River Collection",
            "description": "Collection of rivers layers and their ecosystems",
            "context_group_keys": [
                "water_group"

            ]
        },
        {
            "key": "climate",
            "name": "Climate Collection",
            "description": "Grouping of layers that depicts climate charasteristics",
            "context_group_keys": [
                "rainfall_group",
                "mean_maximum_temperature_group",
                "mean_average_temperature_group",
                "mean_standard_deviation_temperature_group",
                "actual_vapour_group"

            ]
        }
    ]
}
